[
    {
        "name": "Star Sports 1",
        "logo": "https://cdn.jsdelivr.net/gh/HelloPeopleTv4you/tv-logo@refs/heads/main/crichd2-runded/1-by-xfireflix.png",
        "url": "https://pol5.dunyapurkaraja.com:999/hls/star1in.m3u8?md5=IjuHBvC_pVX4_W1n_1WDNw&expires=1745091073",
        "referer": "https://stylisheleg4nt.com",
        "origin": "https://stylisheleg4nt.com"
    },
    {
        "name": "Star Sports 1 Hindi",
        "logo": "https://cdn.jsdelivr.net/gh/HelloPeopleTv4you/tv-logo@refs/heads/main/crichd2-runded/1-by-xfireflix.png",
        "url": "https://pol6.dunyapurkaraja.com:999/hls/starhindi.m3u8?md5=nS8eV1L16b9fNK47sY96hw&expires=1745091073",
        "referer": "https://stylisheleg4nt.com",
        "origin": "https://stylisheleg4nt.com"
    },
    {
        "name": "PTV Sports",
        "logo": "https://cdn.jsdelivr.net/gh/HelloPeopleTv4you/tv-logo@refs/heads/main/crichd2-runded/1-by-xfireflix.png",
        "url": "https://pol6.dunyapurkaraja.com:999/hls/ptvpk.m3u8?md5=pkFAfj2vbvAFz0NZGbMkFw&expires=1745091074",
        "referer": "https://stylisheleg4nt.com",
        "origin": "https://stylisheleg4nt.com"
    },
    {
        "name": "Willow HD",
        "logo": "https://cdn.jsdelivr.net/gh/HelloPeopleTv4you/tv-logo@refs/heads/main/crichd2-runded/1-by-xfireflix.png",
        "url": "https://pol5.dunyapurkaraja.com:999/hls/willowusa.m3u8?md5=63Gqm8_CZeaKhL2P55hiow&expires=1745091074",
        "referer": "https://stylisheleg4nt.com",
        "origin": "https://stylisheleg4nt.com"
    },
    {
        "name": "Willow HD 2",
        "logo": "https://cdn.jsdelivr.net/gh/HelloPeopleTv4you/tv-logo@refs/heads/main/crichd2-runded/1-by-xfireflix.png",
        "url": "https://pol7.dunyapurkaraja.com:999/hls/willowextra.m3u8?md5=aFF79z79cPs1yh4rVEmSow&expires=1745091074",
        "referer": "https://stylisheleg4nt.com",
        "origin": "https://stylisheleg4nt.com"
    },
    {
        "name": "Ten Sports",
        "logo": "https://cdn.jsdelivr.net/gh/HelloPeopleTv4you/tv-logo@refs/heads/main/crichd2-runded/1-by-xfireflix.png",
        "url": "https://pol5.dunyapurkaraja.com:999/hls/tenspk.m3u8?md5=HyJ9Vu3XNdCFYnAPtpFJRA&expires=1745091074",
        "referer": "https://stylisheleg4nt.com",
        "origin": "https://stylisheleg4nt.com"
    },
    {
        "name": "A Sports HD",
        "logo": "https://cdn.jsdelivr.net/gh/HelloPeopleTv4you/tv-logo@refs/heads/main/crichd2-runded/1-by-xfireflix.png",
        "url": "https://pol5.dunyapurkaraja.com:999/hls/asportshd.m3u8?md5=ygkt3Ly2kiJSMR3x1uDSaQ&expires=1745091074",
        "referer": "https://stylisheleg4nt.com",
        "origin": "https://stylisheleg4nt.com"
    },
    {
        "name": "Sky Sports Cricket",
        "logo": "https://cdn.jsdelivr.net/gh/HelloPeopleTv4you/tv-logo@refs/heads/main/crichd2-runded/1-by-xfireflix.png",
        "url": "https://pol7.dunyapurkaraja.com:999/hls/skyscric.m3u8?md5=gINLRg6f4h5uOuwA_lkYLw&expires=1745091074",
        "referer": "https://stylisheleg4nt.com",
        "origin": "https://stylisheleg4nt.com"
    },
    {
        "name": "Sky Sports Main Event",
        "logo": "https://cdn.jsdelivr.net/gh/HelloPeopleTv4you/tv-logo@refs/heads/main/crichd2-runded/1-by-xfireflix.png",
        "error": "Token not found or failed to fetch."
    },
    {
        "name": "TNT 1",
        "logo": "https://cdn.jsdelivr.net/gh/HelloPeopleTv4you/tv-logo@refs/heads/main/crichd2-runded/1-by-xfireflix.png",
        "url": "https://pol6.dunyapurkaraja.com:999/hls/bbtsp1.m3u8?md5=UPs-8-dtwSKw0rh4PQk6qA&expires=1745091074",
        "referer": "https://stylisheleg4nt.com",
        "origin": "https://stylisheleg4nt.com"
    },
    {
        "name": "TNT 2",
        "logo": "https://cdn.jsdelivr.net/gh/HelloPeopleTv4you/tv-logo@refs/heads/main/crichd2-runded/1-by-xfireflix.png",
        "error": "Token not found or failed to fetch."
    },
    {
        "name": "TNT 3",
        "logo": "https://cdn.jsdelivr.net/gh/HelloPeopleTv4you/tv-logo@refs/heads/main/crichd2-runded/1-by-xfireflix.png",
        "url": "https://pol6.dunyapurkaraja.com:999/hls/bbtsp3.m3u8?md5=iaky3Ypt0LYRw7QmIeSDOg&expires=1745091074",
        "referer": "https://stylisheleg4nt.com",
        "origin": "https://stylisheleg4nt.com"
    },
    {
        "name": "TNT 4",
        "logo": "https://cdn.jsdelivr.net/gh/HelloPeopleTv4you/tv-logo@refs/heads/main/crichd2-runded/1-by-xfireflix.png",
        "url": "https://pol7.dunyapurkaraja.com:999/hls/bbtespn.m3u8?md5=gTrEPBB_SbzpLimmbSWM1w&expires=1745091074",
        "referer": "https://stylisheleg4nt.com",
        "origin": "https://stylisheleg4nt.com"
    },
    {
        "name": "Sky Sports 1",
        "logo": "https://cdn.jsdelivr.net/gh/HelloPeopleTv4you/tv-logo@refs/heads/main/crichd2-runded/1-by-xfireflix.png",
        "url": "https://pol7.dunyapurkaraja.com:999/hls/sky1nz.m3u8?md5=EgS9hWwh4OIvEpnKUBqpBQ&expires=1745091075",
        "referer": "https://stylisheleg4nt.com",
        "origin": "https://stylisheleg4nt.com"
    },
    {
        "name": "Sky Sports 2",
        "logo": "https://cdn.jsdelivr.net/gh/HelloPeopleTv4you/tv-logo@refs/heads/main/crichd2-runded/1-by-xfireflix.png",
        "url": "https://pol7.dunyapurkaraja.com:999/hls/sky2nz.m3u8?md5=B9qRlXqPkbvGgt2o0--cLA&expires=1745091075",
        "referer": "https://stylisheleg4nt.com",
        "origin": "https://stylisheleg4nt.com"
    },
    {
        "name": "Sky Sports 3",
        "logo": "https://cdn.jsdelivr.net/gh/HelloPeopleTv4you/tv-logo@refs/heads/main/crichd2-runded/1-by-xfireflix.png",
        "url": "https://pol7.dunyapurkaraja.com:999/hls/sky3nz.m3u8?md5=vICZ7CePSIY4jQulHkxvrQ&expires=1745091075",
        "referer": "https://stylisheleg4nt.com",
        "origin": "https://stylisheleg4nt.com"
    },
    {
        "name": "Sky Sports 4",
        "logo": "https://cdn.jsdelivr.net/gh/HelloPeopleTv4you/tv-logo@refs/heads/main/crichd2-runded/1-by-xfireflix.png",
        "url": "https://pol5.dunyapurkaraja.com:999/hls/sky4nz.m3u8?md5=vAmi20vfD_OpobKBE2TaHA&expires=1745091075",
        "referer": "https://stylisheleg4nt.com",
        "origin": "https://stylisheleg4nt.com"
    },
    {
        "name": "Sky Sports 5",
        "logo": "https://cdn.jsdelivr.net/gh/HelloPeopleTv4you/tv-logo@refs/heads/main/crichd2-runded/1-by-xfireflix.png",
        "url": "https://pol7.dunyapurkaraja.com:999/hls/sky5nz.m3u8?md5=T0WlJGh9Vc6bUERYGTfmEA&expires=1745091075",
        "referer": "https://stylisheleg4nt.com",
        "origin": "https://stylisheleg4nt.com"
    },
    {
        "name": "Sky Sports 6",
        "logo": "https://cdn.jsdelivr.net/gh/HelloPeopleTv4you/tv-logo@refs/heads/main/crichd2-runded/1-by-xfireflix.png",
        "url": "https://pol7.dunyapurkaraja.com:999/hls/sky6nz.m3u8?md5=1amN0LDO37nHcmrl14oLtw&expires=1745091075",
        "referer": "https://stylisheleg4nt.com",
        "origin": "https://stylisheleg4nt.com"
    },
    {
        "name": "Sky Sports 7",
        "logo": "https://cdn.jsdelivr.net/gh/HelloPeopleTv4you/tv-logo@refs/heads/main/crichd2-runded/1-by-xfireflix.png",
        "url": "https://pol5.dunyapurkaraja.com:999/hls/sky7nz.m3u8?md5=zbv7s71fFJdLK3fWZN_3rw&expires=1745091075",
        "referer": "https://stylisheleg4nt.com",
        "origin": "https://stylisheleg4nt.com"
    },
    {
        "name": "Sky Sports 8",
        "logo": "https://cdn.jsdelivr.net/gh/HelloPeopleTv4you/tv-logo@refs/heads/main/crichd2-runded/1-by-xfireflix.png",
        "url": "https://pol5.dunyapurkaraja.com:999/hls/sky8nz.m3u8?md5=BiYbalBnxD_pJbJNse4X3A&expires=1745091075",
        "referer": "https://stylisheleg4nt.com",
        "origin": "https://stylisheleg4nt.com"
    },
    {
        "name": "Sky Sports 9",
        "logo": "https://cdn.jsdelivr.net/gh/HelloPeopleTv4you/tv-logo@refs/heads/main/crichd2-runded/1-by-xfireflix.png",
        "url": "https://pol6.dunyapurkaraja.com:999/hls/sky9nz.m3u8?md5=Mufrlwx9LxHtPkzeI2esGA&expires=1745091075",
        "referer": "https://stylisheleg4nt.com",
        "origin": "https://stylisheleg4nt.com"
    },
    {
        "name": "Sky Cinema",
        "logo": "https://cdn.jsdelivr.net/gh/HelloPeopleTv4you/tv-logo@refs/heads/main/crichd2-runded/1-by-xfireflix.png",
        "error": "Token not found or failed to fetch."
    },
    {
        "name": "Sky Sports Action",
        "logo": "https://cdn.jsdelivr.net/gh/HelloPeopleTv4you/tv-logo@refs/heads/main/crichd2-runded/1-by-xfireflix.png",
        "url": "https://pol6.dunyapurkaraja.com:999/hls/skysact.m3u8?md5=fV6HUGF2KWUXMvbKPhsG5Q&expires=1745091076",
        "referer": "https://stylisheleg4nt.com",
        "origin": "https://stylisheleg4nt.com"
    },
    {
        "name": "Sky Sports Golf",
        "logo": "https://cdn.jsdelivr.net/gh/HelloPeopleTv4you/tv-logo@refs/heads/main/crichd2-runded/1-by-xfireflix.png",
        "url": "https://pol6.dunyapurkaraja.com:999/hls/skysgol.m3u8?md5=75liRZIrgb9C5RZVFzROsQ&expires=1745091076",
        "referer": "https://stylisheleg4nt.com",
        "origin": "https://stylisheleg4nt.com"
    },
    {
        "name": "Sky Sports Premier League",
        "logo": "https://cdn.jsdelivr.net/gh/HelloPeopleTv4you/tv-logo@refs/heads/main/crichd2-runded/1-by-xfireflix.png",
        "url": "https://pol6.dunyapurkaraja.com:999/hls/skysprem.m3u8?md5=aFhfHOnmjKpbdVJfTn4tew&expires=1745091076",
        "referer": "https://stylisheleg4nt.com",
        "origin": "https://stylisheleg4nt.com"
    },
    {
        "name": "Sky Sports Football",
        "logo": "https://cdn.jsdelivr.net/gh/HelloPeopleTv4you/tv-logo@refs/heads/main/crichd2-runded/1-by-xfireflix.png",
        "url": "https://pol5.dunyapurkaraja.com:999/hls/skysfott.m3u8?md5=DxwiFPVriLT0P_FcXFbv3w&expires=1745091076",
        "referer": "https://stylisheleg4nt.com",
        "origin": "https://stylisheleg4nt.com"
    },
    {
        "name": "Sky Sports Plus",
        "logo": "https://cdn.jsdelivr.net/gh/HelloPeopleTv4you/tv-logo@refs/heads/main/crichd2-runded/1-by-xfireflix.png",
        "url": "https://pol5.dunyapurkaraja.com:999/hls/skysare.m3u8?md5=UZmQySgxc7Vq62I5x_AwUQ&expires=1745091076",
        "referer": "https://stylisheleg4nt.com",
        "origin": "https://stylisheleg4nt.com"
    },
    {
        "name": "Sky Sports F1",
        "logo": "https://cdn.jsdelivr.net/gh/HelloPeopleTv4you/tv-logo@refs/heads/main/crichd2-runded/1-by-xfireflix.png",
        "url": "https://pol6.dunyapurkaraja.com:999/hls/skysfor1.m3u8?md5=kajQqz4eDajCF32_BazAlg&expires=1745091076",
        "referer": "https://stylisheleg4nt.com",
        "origin": "https://stylisheleg4nt.com"
    },
    {
        "name": "LaLiGA",
        "logo": "https://cdn.jsdelivr.net/gh/HelloPeopleTv4you/tv-logo@refs/heads/main/crichd2-runded/1-by-xfireflix.png",
        "url": "https://pol5.dunyapurkaraja.com:999/hls/laligauk.m3u8?md5=AuBCPUvlWmbC2DnkrwEE0g&expires=1745091076",
        "referer": "https://stylisheleg4nt.com",
        "origin": "https://stylisheleg4nt.com"
    },
    {
        "name": "Premier Sports 1",
        "logo": "https://cdn.jsdelivr.net/gh/HelloPeopleTv4you/tv-logo@refs/heads/main/crichd2-runded/1-by-xfireflix.png",
        "url": "https://pol6.dunyapurkaraja.com:999/hls/premieruk.m3u8?md5=m7qENGe7LnMdaM7ZIdI17A&expires=1745091076",
        "referer": "https://stylisheleg4nt.com",
        "origin": "https://stylisheleg4nt.com"
    },
    {
        "name": "Premier Sports 2",
        "logo": "https://cdn.jsdelivr.net/gh/HelloPeopleTv4you/tv-logo@refs/heads/main/crichd2-runded/1-by-xfireflix.png",
        "url": "https://pol7.dunyapurkaraja.com:999/hls/hdchnl2.m3u8?md5=5BpGUor187aq8kJ8XI4sIw&expires=1745091076",
        "referer": "https://stylisheleg4nt.com",
        "origin": "https://stylisheleg4nt.com"
    },
    {
        "name": "Super Football",
        "logo": "https://cdn.jsdelivr.net/gh/HelloPeopleTv4you/tv-logo@refs/heads/main/crichd2-runded/1-by-xfireflix.png",
        "url": "https://pol5.dunyapurkaraja.com:999/hls/superfotball.m3u8?md5=WRrJLovTFDftap7bUHty0w&expires=1745091076",
        "referer": "https://stylisheleg4nt.com",
        "origin": "https://stylisheleg4nt.com"
    },
    {
        "name": "Super Premier League",
        "logo": "https://cdn.jsdelivr.net/gh/HelloPeopleTv4you/tv-logo@refs/heads/main/crichd2-runded/1-by-xfireflix.png",
        "url": "https://pol5.dunyapurkaraja.com:999/hls/superpremier.m3u8?md5=D-gunYzD6RzI5tlS8--c7w&expires=1745091076",
        "referer": "https://stylisheleg4nt.com",
        "origin": "https://stylisheleg4nt.com"
    },
    {
        "name": "Astro Cricket",
        "logo": "https://cdn.jsdelivr.net/gh/HelloPeopleTv4you/tv-logo@refs/heads/main/crichd2-runded/1-by-xfireflix.png",
        "url": "https://pol5.dunyapurkaraja.com:999/hls/fox501.m3u8?md5=P_MSO0yzJkyJ1hjID8kq1w&expires=1745091077",
        "referer": "https://stylisheleg4nt.com",
        "origin": "https://stylisheleg4nt.com"
    },
    {
        "name": "ESPN 1",
        "logo": "https://cdn.jsdelivr.net/gh/HelloPeopleTv4you/tv-logo@refs/heads/main/crichd2-runded/1-by-xfireflix.png",
        "url": "https://pol5.dunyapurkaraja.com:999/hls/espnusa.m3u8?md5=wXNWzGvixpdcMK28Yv-Unw&expires=1745091077",
        "referer": "https://stylisheleg4nt.com",
        "origin": "https://stylisheleg4nt.com"
    },
    {
        "name": "ESPN 2",
        "logo": "https://cdn.jsdelivr.net/gh/HelloPeopleTv4you/tv-logo@refs/heads/main/crichd2-runded/1-by-xfireflix.png",
        "error": "Token not found or failed to fetch."
    },
    {
        "name": "Sky Sports Arena",
        "logo": "https://cdn.jsdelivr.net/gh/HelloPeopleTv4you/tv-logo@refs/heads/main/crichd2-runded/1-by-xfireflix.png",
        "url": "https://pol7.dunyapurkaraja.com:999/hls/skysare.m3u8?md5=7MEZGGDX0OAt8goWAuNLWA&expires=1745091077",
        "referer": "https://stylisheleg4nt.com",
        "origin": "https://stylisheleg4nt.com"
    },
    {
        "name": "Sky Sports Mix",
        "logo": "https://cdn.jsdelivr.net/gh/HelloPeopleTv4you/tv-logo@refs/heads/main/crichd2-runded/1-by-xfireflix.png",
        "url": "https://pol7.dunyapurkaraja.com:999/hls/skysmixx.m3u8?md5=apkmRcHGPBKMoebVD4FIww&expires=1745091077",
        "referer": "https://stylisheleg4nt.com",
        "origin": "https://stylisheleg4nt.com"
    },
    {
        "name": "Sky Sports Tennis",
        "logo": "https://cdn.jsdelivr.net/gh/HelloPeopleTv4you/tv-logo@refs/heads/main/crichd2-runded/1-by-xfireflix.png",
        "url": "https://pol7.dunyapurkaraja.com:999/hls/skystennis.m3u8?md5=wxAQhyH-e3B1FMZcAq46gw&expires=1745091077",
        "referer": "https://stylisheleg4nt.com",
        "origin": "https://stylisheleg4nt.com"
    },
    {
        "name": "Fox Cricket 501 HD",
        "logo": "https://cdn.jsdelivr.net/gh/HelloPeopleTv4you/tv-logo@refs/heads/main/crichd2-runded/1-by-xfireflix.png",
        "url": "https://pol7.dunyapurkaraja.com:999/hls/fox501.m3u8?md5=P_MSO0yzJkyJ1hjID8kq1w&expires=1745091077",
        "referer": "https://stylisheleg4nt.com",
        "origin": "https://stylisheleg4nt.com"
    },
    {
        "name": "ESPN US",
        "logo": "https://cdn.jsdelivr.net/gh/HelloPeopleTv4you/tv-logo@refs/heads/main/crichd2-runded/1-by-xfireflix.png",
        "url": "https://pol7.dunyapurkaraja.com:999/hls/espnusa.m3u8?md5=wXNWzGvixpdcMK28Yv-Unw&expires=1745091077",
        "referer": "https://stylisheleg4nt.com",
        "origin": "https://stylisheleg4nt.com"
    },
    {
        "name": "ESPN 2 US",
        "logo": "https://cdn.jsdelivr.net/gh/HelloPeopleTv4you/tv-logo@refs/heads/main/crichd2-runded/1-by-xfireflix.png",
        "error": "Token not found or failed to fetch."
    }
]